{
    "fit_success": true,
    "Qi": {
        "__dtype__": "UFloat",
        "nominal_value": 16182.601927984899,
        "std_dev": 173.83703899074501
    },
    "Qe": {
        "__dtype__": "UFloat",
        "nominal_value": 8265.60841939514,
        "std_dev": 36.732216518874985
    },
    "Ql": {
        "__dtype__": "UFloat",
        "nominal_value": 6477.718207773264,
        "std_dev": 36.46277618863401
    },
    "Qc": {
        "__dtype__": "UFloat",
        "nominal_value": 10801.400426853188,
        "std_dev": 62.72547542269874
    },
    "fr": {
        "__dtype__": "UFloat",
        "nominal_value": 5719786500.787525,
        "std_dev": 2485.257625475153
    },
    "fit_msg": "Summary\n$Q_I$: 16.18$\\pm$0.17 k\n$Q_C$: 10.801$\\pm$0.063 k\n$f_{res}$: 5.7197865$\\pm$2.5e-06 GHz",
    "fit_result": {
        "hanger_func_complex_SI": {
            "success": true,
            "message": "Fit succeeded.",
            "params": {
                "fr": {
                    "name": "fr",
                    "user_data": null,
                    "init_value": 5720025125.62814,
                    "min": 5715000000.0,
                    "max": 5725000000.0,
                    "brute_step": null,
                    "stderr": 2485.257625475153,
                    "correl": {
                        "Ql": 7.802212501929595e-05,
                        "Qe": 0.05346780135624207,
                        "A": 0.22883893997560187,
                        "theta": -0.7992067333590792,
                        "phi_v": -0.23138544044922116,
                        "phi_0": 0.23122119225759089,
                        "alpha": -0.33515186164559146
                    },
                    "value": 5719786500.787525
                },
                "Ql": {
                    "name": "Ql",
                    "user_data": null,
                    "init_value": 2577.186504325074,
                    "min": 57.200251256281405,
                    "max": 113828.50000115068,
                    "brute_step": null,
                    "stderr": 36.46277618863401,
                    "correl": {
                        "fr": 7.802212501929595e-05,
                        "Qe": 0.7991894853040223,
                        "A": -0.3130893612030615,
                        "theta": 0.0532992759650132,
                        "phi_v": 0.3187345538779319,
                        "phi_0": -0.3188619390434702,
                        "alpha": -0.20696178301741444
                    },
                    "value": 6477.718207773264
                },
                "Qe": {
                    "name": "Qe",
                    "user_data": null,
                    "init_value": 2526.153108199825,
                    "min": 0,
                    "max": Infinity,
                    "brute_step": null,
                    "stderr": 36.732216518874985,
                    "correl": {
                        "fr": 0.05346780135624207,
                        "Ql": 0.7991894853040223,
                        "A": -0.24029108819675174,
                        "theta": -8.963934227128019e-05,
                        "phi_v": 0.3939013339454947,
                        "phi_0": -0.3940753673842924,
                        "alpha": -0.3066736081164216
                    },
                    "value": 8265.60841939514
                },
                "A": {
                    "name": "A",
                    "user_data": null,
                    "init_value": 0.003466450896224672,
                    "min": 0,
                    "max": Infinity,
                    "brute_step": null,
                    "stderr": 2.910686951344037e-06,
                    "correl": {
                        "fr": 0.22883893997560187,
                        "Ql": -0.3130893612030615,
                        "Qe": -0.24029108819675174,
                        "theta": -0.3178483039680843,
                        "phi_v": -0.14132165955545106,
                        "phi_0": 0.14133973410935918,
                        "alpha": -0.011482604472611955
                    },
                    "value": 0.0036756012734875387
                },
                "theta": {
                    "name": "theta",
                    "user_data": null,
                    "init_value": 0,
                    "min": -1.5707963267948966,
                    "max": 1.5707963267948966,
                    "brute_step": null,
                    "stderr": 0.004444118562498687,
                    "correl": {
                        "fr": -0.7992067333590792,
                        "Ql": 0.0532992759650132,
                        "Qe": -8.963934227128019e-05,
                        "A": -0.3178483039680843,
                        "phi_v": 0.33697517622283046,
                        "phi_0": -0.3368456251887687,
                        "alpha": 0.4179989197261653
                    },
                    "value": 0.6993902053635375
                },
                "phi_v": {
                    "name": "phi_v",
                    "user_data": null,
                    "init_value": -1.3591832474688714e-06,
                    "min": -Infinity,
                    "max": Infinity,
                    "brute_step": null,
                    "stderr": 2.78176258765933e-10,
                    "correl": {
                        "fr": -0.23138544044922116,
                        "Ql": 0.3187345538779319,
                        "Qe": 0.3939013339454947,
                        "A": -0.14132165955545106,
                        "theta": 0.33697517622283046,
                        "phi_0": -0.9999998727386442,
                        "alpha": 0.07457454247227746
                    },
                    "value": -1.3044846003216671e-06
                },
                "phi_0": {
                    "name": "phi_0",
                    "user_data": null,
                    "init_value": 7766.403300828441,
                    "min": -Infinity,
                    "max": Infinity,
                    "brute_step": null,
                    "stderr": 1.591113091518591,
                    "correl": {
                        "fr": 0.23122119225759089,
                        "Ql": -0.3188619390434702,
                        "Qe": -0.3940753673842924,
                        "A": 0.14133973410935918,
                        "theta": -0.3368456251887687,
                        "phi_v": -0.9999998727386442,
                        "alpha": -0.07446695079194553
                    },
                    "value": 7453.85886962249
                },
                "alpha": {
                    "name": "alpha",
                    "user_data": null,
                    "init_value": 0,
                    "min": -1,
                    "max": 1,
                    "brute_step": null,
                    "stderr": 1.590911705757215,
                    "correl": {
                        "fr": -0.33515186164559146,
                        "Ql": -0.20696178301741444,
                        "Qe": -0.3066736081164216,
                        "A": -0.011482604472611955,
                        "theta": 0.4179989197261653,
                        "phi_v": 0.07457454247227746,
                        "phi_0": -0.07446695079194553
                    },
                    "value": -0.2334919292480877
                },
                "Qi": {
                    "name": "Qi",
                    "user_data": null,
                    "init_value": -127570.73196409066,
                    "min": -Infinity,
                    "max": Infinity,
                    "brute_step": null,
                    "stderr": 173.83703899074501,
                    "correl": null,
                    "value": 16182.601927984899
                },
                "Qc": {
                    "name": "Qc",
                    "user_data": null,
                    "init_value": 2526.153108199825,
                    "min": -Infinity,
                    "max": Infinity,
                    "brute_step": null,
                    "stderr": 62.72547542269874,
                    "correl": null,
                    "value": 10801.400426853188
                }
            }
        }
    }
}