{
    "amplitude": {
        "__dtype__": "UFloat",
        "nominal_value": 348355.0627736523,
        "std_dev": 19389.939176200594
    },
    "frequency": {
        "__dtype__": "UFloat",
        "nominal_value": 9.378712530636125,
        "std_dev": 0.31193185421330194
    },
    "shift": {
        "__dtype__": "UFloat",
        "nominal_value": 0.9962834196529569,
        "std_dev": 0.05561450345562936
    },
    "offset": {
        "__dtype__": "UFloat",
        "nominal_value": 6106810578.373318,
        "std_dev": 50137.588471884395
    },
    "offset_0": {
        "__dtype__": "UFloat",
        "nominal_value": 0.061257118742605546,
        "std_dev": 0.006270106958344766
    },
    "freq_0": 6107158933.436091,
    "fit_success": true,
    "fit_msg": "Summary:\nf_0: 6.1072 GHz\noffset_0: 61.3$\\pm$6.3 mV\n",
    "fit_result": {
        "sin": {
            "success": true,
            "message": "Fit succeeded.",
            "params": {
                "amplitude": {
                    "name": "amplitude",
                    "user_data": null,
                    "init_value": 340539.89071581676,
                    "min": 0,
                    "max": Infinity,
                    "brute_step": null,
                    "stderr": 19389.939176200594,
                    "correl": {
                        "frequency": -0.1426176518893771,
                        "shift": 0.09995765897130468
                    },
                    "value": 348355.0627736523
                },
                "frequency": {
                    "name": "frequency",
                    "user_data": null,
                    "init_value": 10.053096491487338,
                    "min": 0,
                    "max": Infinity,
                    "brute_step": null,
                    "stderr": 0.31193185421330194,
                    "correl": {
                        "amplitude": -0.1426176518893771,
                        "shift": -0.27144616430342355
                    },
                    "value": 9.378712530636125
                },
                "shift": {
                    "name": "shift",
                    "user_data": null,
                    "init_value": 1.1423973285781066,
                    "min": -6.283195307179586,
                    "max": 6.283195307179586,
                    "brute_step": null,
                    "stderr": 0.05561450345562936,
                    "correl": {
                        "amplitude": 0.09995765897130468,
                        "frequency": -0.27144616430342355
                    },
                    "value": 0.9962834196529569
                },
                "offset": {
                    "name": "offset",
                    "user_data": null,
                    "init_value": 6106810578.373318,
                    "min": -Infinity,
                    "max": Infinity,
                    "brute_step": null,
                    "stderr": 50137.588471884395,
                    "correl": null,
                    "value": 6106810578.373318
                }
            }
        }
    }
}