{
    "fit_success": false,
    "Qi": {
        "__dtype__": "UFloat",
        "nominal_value": 2142.2680189381567,
        "std_dev": NaN
    },
    "Qe": {
        "__dtype__": "UFloat",
        "nominal_value": 1253.5633141846247,
        "std_dev": NaN
    },
    "Ql": {
        "__dtype__": "UFloat",
        "nominal_value": 808.0845044744387,
        "std_dev": NaN
    },
    "Qc": {
        "__dtype__": "UFloat",
        "nominal_value": 1297.522845821488,
        "std_dev": NaN
    },
    "fr": {
        "__dtype__": "UFloat",
        "nominal_value": 5838236578.734875,
        "std_dev": NaN
    },
    "fit_msg": "Warning: fit failed. lmfit was not\nable to fit the data.",
    "fit_result": {
        "hanger_func_complex_SI": {
            "success": false,
            "message": "Tolerance seems to be too small. Could not estimate error-bars.",
            "params": {
                "fr": {
                    "name": "fr",
                    "user_data": null,
                    "init_value": 5836959798.994975,
                    "min": 5825000000.0,
                    "max": 5845000000.0,
                    "brute_step": null,
                    "stderr": null,
                    "correl": null,
                    "value": 5838236578.734875
                },
                "Ql": {
                    "name": "Ql",
                    "user_data": null,
                    "init_value": 1314.9360090035048,
                    "min": 29.184798994974877,
                    "max": 58077.750000036,
                    "brute_step": null,
                    "stderr": null,
                    "correl": null,
                    "value": 808.0845044744387
                },
                "Qe": {
                    "name": "Qe",
                    "user_data": null,
                    "init_value": 1288.8976721915542,
                    "min": 0,
                    "max": Infinity,
                    "brute_step": null,
                    "stderr": null,
                    "correl": null,
                    "value": 1253.5633141846247
                },
                "A": {
                    "name": "A",
                    "user_data": null,
                    "init_value": 4.083688342228484e-05,
                    "min": 0,
                    "max": Infinity,
                    "brute_step": null,
                    "stderr": null,
                    "correl": null,
                    "value": 5.323654797773081e-05
                },
                "theta": {
                    "name": "theta",
                    "user_data": null,
                    "init_value": 0,
                    "min": -1.5707963267948966,
                    "max": 1.5707963267948966,
                    "brute_step": null,
                    "stderr": null,
                    "correl": null,
                    "value": -0.26104648526735375
                },
                "phi_v": {
                    "name": "phi_v",
                    "user_data": null,
                    "init_value": 2.714959521947959e-07,
                    "min": -Infinity,
                    "max": Infinity,
                    "brute_step": null,
                    "stderr": null,
                    "correl": null,
                    "value": 2.5555166112283076e-07
                },
                "phi_0": {
                    "name": "phi_0",
                    "user_data": null,
                    "init_value": -1581.1134189290162,
                    "min": -Infinity,
                    "max": Infinity,
                    "brute_step": null,
                    "stderr": null,
                    "correl": null,
                    "value": -1488.130052796623
                },
                "alpha": {
                    "name": "alpha",
                    "user_data": null,
                    "init_value": 0,
                    "min": -1,
                    "max": 1,
                    "brute_step": null,
                    "stderr": null,
                    "correl": null,
                    "value": 0.9992885870770141
                },
                "Qi": {
                    "name": "Qi",
                    "user_data": null,
                    "init_value": -65089.332445673805,
                    "min": -Infinity,
                    "max": Infinity,
                    "brute_step": null,
                    "stderr": null,
                    "correl": null,
                    "value": 2142.2680189381567
                },
                "Qc": {
                    "name": "Qc",
                    "user_data": null,
                    "init_value": 1288.8976721915542,
                    "min": -Infinity,
                    "max": Infinity,
                    "brute_step": null,
                    "stderr": null,
                    "correl": null,
                    "value": 1297.522845821488
                }
            }
        }
    }
}