{
    "fit_success": false,
    "Qi": {
        "__dtype__": "UFloat",
        "nominal_value": 12491.43124648532,
        "std_dev": NaN
    },
    "Qe": {
        "__dtype__": "UFloat",
        "nominal_value": 4100.650611353852,
        "std_dev": NaN
    },
    "Ql": {
        "__dtype__": "UFloat",
        "nominal_value": 4124.69062194833,
        "std_dev": NaN
    },
    "Qc": {
        "__dtype__": "UFloat",
        "nominal_value": 6158.107634649137,
        "std_dev": NaN
    },
    "fr": {
        "__dtype__": "UFloat",
        "nominal_value": 5905343094.719034,
        "std_dev": NaN
    },
    "fit_msg": "Warning: fit failed. lmfit was not\nable to fit the data.",
    "fit_result": {
        "hanger_func_complex_SI": {
            "success": false,
            "message": "Tolerance seems to be too small. Could not estimate error-bars.",
            "params": {
                "fr": {
                    "name": "fr",
                    "user_data": null,
                    "init_value": 5905854271.356784,
                    "min": 5895000000.0,
                    "max": 5915000000.0,
                    "brute_step": null,
                    "stderr": null,
                    "correl": null,
                    "value": 5905343094.719034
                },
                "Ql": {
                    "name": "Ql",
                    "user_data": null,
                    "init_value": 1330.4563870169764,
                    "min": 29.529271356783923,
                    "max": 58763.25000003642,
                    "brute_step": null,
                    "stderr": null,
                    "correl": null,
                    "value": 4124.69062194833
                },
                "Qe": {
                    "name": "Qe",
                    "user_data": null,
                    "init_value": 1304.110715986937,
                    "min": 0,
                    "max": Infinity,
                    "brute_step": null,
                    "stderr": null,
                    "correl": null,
                    "value": 4100.650611353852
                },
                "A": {
                    "name": "A",
                    "user_data": null,
                    "init_value": 0.1818090027979048,
                    "min": 0,
                    "max": Infinity,
                    "brute_step": null,
                    "stderr": null,
                    "correl": null,
                    "value": 0.1897400224599366
                },
                "theta": {
                    "name": "theta",
                    "user_data": null,
                    "init_value": 0,
                    "min": -1.5707963267948966,
                    "max": 1.5707963267948966,
                    "brute_step": null,
                    "stderr": null,
                    "correl": null,
                    "value": 0.842104029396606
                },
                "phi_v": {
                    "name": "phi_v",
                    "user_data": null,
                    "init_value": -1.2024153061411582e-07,
                    "min": -Infinity,
                    "max": Infinity,
                    "brute_step": null,
                    "stderr": null,
                    "correl": null,
                    "value": -1.0074878086652118e-07
                },
                "phi_0": {
                    "name": "phi_0",
                    "user_data": null,
                    "init_value": 706.8471487190523,
                    "min": -Infinity,
                    "max": Infinity,
                    "brute_step": null,
                    "stderr": null,
                    "correl": null,
                    "value": 591.9513988855948
                },
                "alpha": {
                    "name": "alpha",
                    "user_data": null,
                    "init_value": 0,
                    "min": -1,
                    "max": 1,
                    "brute_step": null,
                    "stderr": null,
                    "correl": null,
                    "value": -0.999320121767223
                },
                "Qi": {
                    "name": "Qi",
                    "user_data": null,
                    "init_value": -65857.59115733995,
                    "min": -Infinity,
                    "max": Infinity,
                    "brute_step": null,
                    "stderr": null,
                    "correl": null,
                    "value": 12491.43124648532
                },
                "Qc": {
                    "name": "Qc",
                    "user_data": null,
                    "init_value": 1304.110715986937,
                    "min": -Infinity,
                    "max": Infinity,
                    "brute_step": null,
                    "stderr": null,
                    "correl": null,
                    "value": 6158.107634649137
                }
            }
        }
    }
}