{
    "fit_success": true,
    "Qi": {
        "__dtype__": "UFloat",
        "nominal_value": 1566.5106362107224,
        "std_dev": 3378.06598423119
    },
    "Qe": {
        "__dtype__": "UFloat",
        "nominal_value": 157965.40161936247,
        "std_dev": 526666.3858396088
    },
    "Ql": {
        "__dtype__": "UFloat",
        "nominal_value": 1564.1881338733033,
        "std_dev": 3397.1912282042304
    },
    "Qc": {
        "__dtype__": "UFloat",
        "nominal_value": 1055033.3187049774,
        "std_dev": 23509371.198390704
    },
    "fr": {
        "__dtype__": "UFloat",
        "nominal_value": 5795481691.894081,
        "std_dev": 4024291.131511679
    },
    "fit_msg": "Summary\n$Q_I$: 1.6$\\pm$3.4 k\n$Q_C$: 1$\\pm$24 M\n$f_{res}$: 5.7955$\\pm$0.0040 GHz",
    "fit_result": {
        "hanger_func_complex_SI": {
            "success": true,
            "message": "Fit succeeded.",
            "params": {
                "fr": {
                    "name": "fr",
                    "user_data": null,
                    "init_value": 5795050251.256282,
                    "min": 5795000000.0,
                    "max": 5805000000.0,
                    "brute_step": null,
                    "stderr": 4024291.131511679,
                    "correl": {
                        "Ql": -3.847257842295691e-05,
                        "Qe": 0.44516039462888035,
                        "A": 0.3347012366974841,
                        "theta": -0.8627516590541454,
                        "phi_v": 0.563547880295756,
                        "phi_0": -0.5641291777957419,
                        "alpha": 0.5440713476657183
                    },
                    "value": 5795481691.894081
                },
                "Ql": {
                    "name": "Ql",
                    "user_data": null,
                    "init_value": 2610.989457460338,
                    "min": 57.95050251256282,
                    "max": 115321.50000116578,
                    "brute_step": null,
                    "stderr": 3397.1912282042304,
                    "correl": {
                        "fr": -3.847257842295691e-05,
                        "Qe": 0.8625719559181867,
                        "A": -0.8409904064686413,
                        "theta": 0.4449074784059592,
                        "phi_v": 0.5873450984650593,
                        "phi_0": -0.5870110340160675,
                        "alpha": -0.605686553544054
                    },
                    "value": 1564.1881338733033
                },
                "Qe": {
                    "name": "Qe",
                    "user_data": null,
                    "init_value": 2559.2866959264697,
                    "min": 0,
                    "max": Infinity,
                    "brute_step": null,
                    "stderr": 526666.3858396088,
                    "correl": {
                        "fr": 0.44516039462888035,
                        "Ql": 0.8625719559181867,
                        "A": -0.6289015049653723,
                        "theta": -0.000323727201025061,
                        "phi_v": 0.8676473861665349,
                        "phi_0": -0.8675850815574403,
                        "alpha": -0.31249098337525416
                    },
                    "value": 157965.40161936247
                },
                "A": {
                    "name": "A",
                    "user_data": null,
                    "init_value": 0.050517662656311746,
                    "min": 0,
                    "max": Infinity,
                    "brute_step": null,
                    "stderr": 0.0008528259236152381,
                    "correl": {
                        "fr": 0.3347012366974841,
                        "Ql": -0.8409904064686413,
                        "Qe": -0.6289015049653723,
                        "theta": -0.7389864325477415,
                        "phi_v": -0.3759312911470234,
                        "phi_0": 0.3753600253479374,
                        "alpha": 0.9152031475832154
                    },
                    "value": 0.05061270933538964
                },
                "theta": {
                    "name": "theta",
                    "user_data": null,
                    "init_value": 0,
                    "min": -1.5707963267948966,
                    "max": 1.5707963267948966,
                    "brute_step": null,
                    "stderr": 3.3365583205453637,
                    "correl": {
                        "fr": -0.8627516590541454,
                        "Ql": 0.4449074784059592,
                        "Qe": -0.000323727201025061,
                        "A": -0.7389864325477415,
                        "phi_v": -0.24901780624061964,
                        "phi_0": 0.24971703751299934,
                        "alpha": -0.8468170469592864
                    },
                    "value": 1.4205056793813329
                },
                "phi_v": {
                    "name": "phi_v",
                    "user_data": null,
                    "init_value": -1.2923126135693667e-06,
                    "min": -Infinity,
                    "max": Infinity,
                    "brute_step": null,
                    "stderr": 1.658754532192701e-09,
                    "correl": {
                        "fr": 0.563547880295756,
                        "Ql": 0.5873450984650593,
                        "Qe": 0.8676473861665349,
                        "A": -0.3759312911470234,
                        "theta": -0.24901780624061964,
                        "phi_0": -0.9999996963080856,
                        "alpha": -0.07432275272770272
                    },
                    "value": -1.293849354404673e-06
                },
                "phi_0": {
                    "name": "phi_0",
                    "user_data": null,
                    "init_value": 7490.6717799447415,
                    "min": -Infinity,
                    "max": Infinity,
                    "brute_step": null,
                    "stderr": 9.628106280146158,
                    "correl": {
                        "fr": -0.5641291777957419,
                        "Ql": -0.5870110340160675,
                        "Qe": -0.8675850815574403,
                        "A": 0.3753600253479374,
                        "theta": 0.24971703751299934,
                        "phi_v": -0.9999996963080856,
                        "alpha": 0.07368725392407864
                    },
                    "value": 7499.588023322898
                },
                "alpha": {
                    "name": "alpha",
                    "user_data": null,
                    "init_value": 0,
                    "min": -1,
                    "max": 1,
                    "brute_step": null,
                    "stderr": 9.222190139409843,
                    "correl": {
                        "fr": 0.5440713476657183,
                        "Ql": -0.605686553544054,
                        "Qe": -0.31249098337525416,
                        "A": 0.9152031475832154,
                        "theta": -0.8468170469592864,
                        "phi_v": -0.07432275272770272,
                        "phi_0": 0.07368725392407864
                    },
                    "value": 0.9958595675938389
                },
                "Qi": {
                    "name": "Qi",
                    "user_data": null,
                    "init_value": -129243.97814428587,
                    "min": -Infinity,
                    "max": Infinity,
                    "brute_step": null,
                    "stderr": 3378.06598423119,
                    "correl": null,
                    "value": 1566.5106362107224
                },
                "Qc": {
                    "name": "Qc",
                    "user_data": null,
                    "init_value": 2559.2866959264697,
                    "min": -Infinity,
                    "max": Infinity,
                    "brute_step": null,
                    "stderr": 23509371.198390704,
                    "correl": null,
                    "value": 1055033.3187049774
                }
            }
        }
    }
}