{
    "T2*": {
        "__dtype__": "UFloat",
        "nominal_value": 8.55970318314192e-06,
        "std_dev": 1.7034569634266729e-06
    },
    "fitted_detuning": {
        "__dtype__": "UFloat",
        "nominal_value": 4494141.9071142655,
        "std_dev": 3722.468615503637
    },
    "detuning": {
        "__dtype__": "UFloat",
        "nominal_value": -5505858.0928857345,
        "std_dev": 3722.468615503637
    },
    "fit_success": true,
    "fit_msg": "Summary\n$T_2^*$: 8.6$\\pm$1.7 \u03bcs\n\nartificial detuning: 10 MHz\nfitted detuning: 4.4941$\\pm$0.0037 MHz\nactual detuning: -5.5059$\\pm$0.0037 MHz\n",
    "fit_result": {
        "Ramsey_decay": {
            "success": true,
            "message": "Fit succeeded.",
            "params": {
                "tau": {
                    "name": "tau",
                    "user_data": null,
                    "init_value": 5.314666666666666e-06,
                    "min": 0,
                    "max": Infinity,
                    "brute_step": null,
                    "stderr": 1.7034569634266729e-06,
                    "correl": {
                        "frequency": 0.0043684961439515845,
                        "phase": -0.003273549438072776,
                        "amplitude": -0.7956449468989997,
                        "offset": 0.016758904511261004
                    },
                    "value": 8.55970318314192e-06
                },
                "n_factor": {
                    "name": "n_factor",
                    "user_data": null,
                    "init_value": 1,
                    "min": -Infinity,
                    "max": Infinity,
                    "brute_step": null,
                    "stderr": 0.0,
                    "correl": null,
                    "value": 1
                },
                "frequency": {
                    "name": "frequency",
                    "user_data": null,
                    "init_value": 4500000.0,
                    "min": 0,
                    "max": Infinity,
                    "brute_step": null,
                    "stderr": 3722.468615503637,
                    "correl": {
                        "tau": 0.0043684961439515845,
                        "phase": -0.8002119635640349,
                        "amplitude": -0.0029720255056208582,
                        "offset": -0.01447061313175402
                    },
                    "value": 4494141.9071142655
                },
                "phase": {
                    "name": "phase",
                    "user_data": null,
                    "init_value": -43.81893433227044,
                    "min": -Infinity,
                    "max": Infinity,
                    "brute_step": null,
                    "stderr": 0.08284674314528175,
                    "correl": {
                        "tau": -0.003273549438072776,
                        "frequency": -0.8002119635640349,
                        "amplitude": 0.002662979876188169,
                        "offset": 0.014762718115447946
                    },
                    "value": -44.48962542699098
                },
                "amplitude": {
                    "name": "amplitude",
                    "user_data": null,
                    "init_value": 0.00023576488612507898,
                    "min": 0,
                    "max": Infinity,
                    "brute_step": null,
                    "stderr": 1.3542336707993583e-05,
                    "correl": {
                        "tau": -0.7956449468989997,
                        "frequency": -0.0029720255056208582,
                        "phase": 0.002662979876188169,
                        "offset": -0.015325129824681066
                    },
                    "value": 0.00016597636517401426
                },
                "offset": {
                    "name": "offset",
                    "user_data": null,
                    "init_value": 0.0010411415538597963,
                    "min": -Infinity,
                    "max": Infinity,
                    "brute_step": null,
                    "stderr": 3.916669739299045e-06,
                    "correl": {
                        "tau": 0.016758904511261004,
                        "frequency": -0.01447061313175402,
                        "phase": 0.014762718115447946,
                        "amplitude": -0.015325129824681066
                    },
                    "value": 0.0010408815627514405
                }
            }
        }
    }
}