{
    "fit_success": true,
    "Qi": {
        "__dtype__": "UFloat",
        "nominal_value": 12386.13045354139,
        "std_dev": 184.9378063092762
    },
    "Qe": {
        "__dtype__": "UFloat",
        "nominal_value": 8290.668501972208,
        "std_dev": 53.87875905605692
    },
    "Ql": {
        "__dtype__": "UFloat",
        "nominal_value": 5741.42645606936,
        "std_dev": 49.71330570206231
    },
    "Qc": {
        "__dtype__": "UFloat",
        "nominal_value": 10702.366441205535,
        "std_dev": 89.77784669028975
    },
    "fr": {
        "__dtype__": "UFloat",
        "nominal_value": 5719781677.731399,
        "std_dev": 4313.388788154951
    },
    "fit_msg": "Summary\n$Q_I$: 12.39$\\pm$0.18 k\n$Q_C$: 10.702$\\pm$0.090 k\n$f_{res}$: 5.7197817$\\pm$4.3e-06 GHz",
    "fit_result": {
        "hanger_func_complex_SI": {
            "success": true,
            "message": "Fit succeeded.",
            "params": {
                "fr": {
                    "name": "fr",
                    "user_data": null,
                    "init_value": 5720107023.411371,
                    "min": 5708000000.0,
                    "max": 5728000000.0,
                    "brute_step": null,
                    "stderr": 4313.388788154951,
                    "correl": {
                        "Ql": 0.00017302720822379142,
                        "Qe": 0.0215935817463621,
                        "A": 0.14582875842687035,
                        "theta": -0.7665590467015961,
                        "phi_v": -0.2517771777879407,
                        "phi_0": 0.25157334241599505,
                        "alpha": 0.1704539155080851
                    },
                    "value": 5719781677.731399
                },
                "Ql": {
                    "name": "Ql",
                    "user_data": null,
                    "init_value": 1579.5418128287831,
                    "min": 28.60053511705686,
                    "max": 85515.6000003099,
                    "brute_step": null,
                    "stderr": 49.71330570206231,
                    "correl": {
                        "fr": 0.00017302720822379142,
                        "Qe": 0.7665131351288201,
                        "A": -0.2782215185197363,
                        "theta": 0.021215568205931637,
                        "phi_v": 0.16908571804872513,
                        "phi_0": -0.16930960403360892,
                        "alpha": 0.25097191157679144
                    },
                    "value": 5741.42645606936
                },
                "Qe": {
                    "name": "Qe",
                    "user_data": null,
                    "init_value": 1548.2637571292032,
                    "min": 0,
                    "max": Infinity,
                    "brute_step": null,
                    "stderr": 53.87875905605692,
                    "correl": {
                        "fr": 0.0215935817463621,
                        "Ql": 0.7665131351288201,
                        "A": -0.25404556235788106,
                        "theta": -0.00021449175600594676,
                        "phi_v": 0.2181092424155776,
                        "phi_0": -0.21841218018678474,
                        "alpha": 0.31232137800527104
                    },
                    "value": 8290.668501972208
                },
                "A": {
                    "name": "A",
                    "user_data": null,
                    "init_value": 0.005846967647023667,
                    "min": 0,
                    "max": Infinity,
                    "brute_step": null,
                    "stderr": 5.2746068536159095e-06,
                    "correl": {
                        "fr": 0.14582875842687035,
                        "Ql": -0.2782215185197363,
                        "Qe": -0.25404556235788106,
                        "theta": -0.20198362735580816,
                        "phi_v": -0.11252148151040965,
                        "phi_0": 0.11256870606327725,
                        "alpha": -0.3540240408662035
                    },
                    "value": 0.006002357511994516
                },
                "theta": {
                    "name": "theta",
                    "user_data": null,
                    "init_value": 0,
                    "min": -1.5707963267948966,
                    "max": 1.5707963267948966,
                    "brute_step": null,
                    "stderr": 0.0064993482604756014,
                    "correl": {
                        "fr": -0.7665590467015961,
                        "Ql": 0.021215568205931637,
                        "Qe": -0.00021449175600594676,
                        "A": -0.20198362735580816,
                        "phi_v": 0.31325086134024704,
                        "phi_0": -0.31309620369077557,
                        "alpha": -0.21984660285008187
                    },
                    "value": 0.6846230050388709
                },
                "phi_v": {
                    "name": "phi_v",
                    "user_data": null,
                    "init_value": -1.0287738015973913e-07,
                    "min": -Infinity,
                    "max": Infinity,
                    "brute_step": null,
                    "stderr": 1.4315161691776379e-10,
                    "correl": {
                        "fr": -0.2517771777879407,
                        "Ql": 0.16908571804872513,
                        "Qe": 0.2181092424155776,
                        "A": -0.11252148151040965,
                        "theta": 0.31325086134024704,
                        "phi_0": -0.9999994950646902,
                        "alpha": -0.0042718864980585865
                    },
                    "value": -7.243339912115594e-08
                },
                "phi_0": {
                    "name": "phi_0",
                    "user_data": null,
                    "init_value": 586.961859998132,
                    "min": -Infinity,
                    "max": Infinity,
                    "brute_step": null,
                    "stderr": 0.8184843475924491,
                    "correl": {
                        "fr": 0.25157334241599505,
                        "Ql": -0.16930960403360892,
                        "Qe": -0.21841218018678474,
                        "A": 0.11256870606327725,
                        "theta": -0.31309620369077557,
                        "phi_v": -0.9999994950646902,
                        "alpha": 0.004144342994103108
                    },
                    "value": 413.17895750264347
                },
                "alpha": {
                    "name": "alpha",
                    "user_data": null,
                    "init_value": 0,
                    "min": -1,
                    "max": 1,
                    "brute_step": null,
                    "stderr": 0.8874950458575905,
                    "correl": {
                        "fr": 0.1704539155080851,
                        "Ql": 0.25097191157679144,
                        "Qe": 0.31232137800527104,
                        "A": -0.3540240408662035,
                        "theta": -0.21984660285008187,
                        "phi_v": -0.0042718864980585865,
                        "phi_0": 0.004144342994103108
                    },
                    "value": -0.9999744988969396
                },
                "Qi": {
                    "name": "Qi",
                    "user_data": null,
                    "init_value": -78187.31973502523,
                    "min": -Infinity,
                    "max": Infinity,
                    "brute_step": null,
                    "stderr": 184.9378063092762,
                    "correl": null,
                    "value": 12386.13045354139
                },
                "Qc": {
                    "name": "Qc",
                    "user_data": null,
                    "init_value": 1548.2637571292032,
                    "min": -Infinity,
                    "max": Infinity,
                    "brute_step": null,
                    "stderr": 89.77784669028975,
                    "correl": null,
                    "value": 10702.366441205535
                }
            }
        }
    }
}